amberpdf/__init__.py
amberpdf/core.py
amberpdf-0.1.4.dist-info/LICENSE
amberpdf-0.1.4.dist-info/METADATA
amberpdf-0.1.4.dist-info/WHEEL
amberpdf-0.1.4.dist-info/top_level.txt
amberpdf-0.1.4.dist-info/RECORD
