Metadata-Version: 2.1
Name: amberpdf
Version: 0.1.4
Summary: Librería que procesa un PDF mixto (texto e imágenes/tablas) y extrae el contenido en orden
Home-page: https://github.com/amberpdf
Author: Paulo Suclly
Author-email: paulo.suclly@pucp.edu.pe
Classifier: Programming Language :: Python :: 3
Classifier: License :: OSI Approved :: MIT License
Classifier: Operating System :: OS Independent
Requires-Python: >=3.6
License-File: LICENSE
Requires-Dist: PyMuPDF>=1.18.0
Requires-Dist: boto3>=1.26.0
Requires-Dist: pandas
